{"type": "Feature", "id": 12514791, "properties": {"woe:id": 12514791, "woe:parent_id": 56438656, "woe:name": "Sale Airport", "woe:placetype": 14, "woe:placetype_name": "Airport", "woe:lang": "ENG", "iso:country": "MA", "meta:provider": ["geoplanet:7.3.1", "geoplanet:7.3.2", "geoplanet:7.4.0", "geoplanet:7.4.1", "geoplanet:7.5.1", "geoplanet:7.5.2", "geoplanet:7.6.0", "geoplanet:7.8.1", "geoplanet:7.9.0", "geoplanet:7.10.0", "geoplanet:8.0.0", "woeplanet:8.0.0"], "meta:indexed": "2020-08-20T20:51:46.222247", "woe:alias_ENG_V": ["RBA Airport", "RBA"], "meta:updated": "2020-08-22T02:46:43.528005", "woe:hierarchy": {"continent": 24865670, "country": 23424893, "town": 0, "planet": 1, "county": 56120073, "suburb": 0, "state": 56120059, "region": 0, "localadmin": 56438656}, "woe:timezone_id": 28350694, "woe:hash": "ey51wnpj5f5n", "woe:centroid": [-6.7578, 34.047501], "geom:latitude": 34.047501, "geom:longitude": -6.7578, "geom:hash": "ey51wnpj5f5n", "woe:latitude": 34.047501, "geom:centroid": [-6.7578, 34.047501], "woe:longitude": -6.7578, "woe:repo": "woeplanet-airport-ma"}, "geometry": {"coordinates": [-6.7578, 34.047501], "type": "Point"}}