{"type": "Feature", "id": 12514794, "geometry": {"type": "Point", "coordinates": [-2.9222, 35.1544]}, "properties": {"woe:id": 12514794, "woe:parent_id": 1538173, "woe:name": "Taouima Airport", "woe:placetype": 14, "woe:placetype_name": "Airport", "woe:lang": "ENG", "iso:country": "MA", "meta:provider": ["geoplanet:7.3.1", "geoplanet:7.3.2", "geoplanet:7.4.0", "geoplanet:7.4.1", "geoplanet:7.5.1", "geoplanet:7.5.2", "geoplanet:7.6.0", "geoplanet:7.8.1", "geoplanet:7.9.0", "geoplanet:7.10.0", "geoplanet:8.0.0", "woeplanet:8.0.0"], "meta:indexed": "2020-08-20T20:51:46.225113", "meta:updated": "2020-10-14T11:06:44.450353", "woe:hierarchy": {"continent": 24865670, "country": 23424893, "town": 0, "planet": 1, "county": 2346209, "suburb": 0, "state": 56120058, "region": 0, "localadmin": 56439626}, "woe:timezone_id": 28350694, "woe:hash": "eyjzvx8j5z1u", "woe:centroid": [-2.9222, 35.1544], "geom:latitude": 35.1544, "geom:longitude": -2.9222, "geom:hash": "eyjzvx8j5z1u", "woe:latitude": 35.1544, "geom:centroid": [-2.9222, 35.1544], "woe:longitude": -2.9222, "woe:repo": "woeplanet-airport-ma", "geom:area": 0.0, "woe:scale": 19}}